spotify_scraper/__init__.py
spotify_scraper/__main__.py
spotify_scraper/client.py
spotify_scraper/config_manager.py
spotify_scraper/constants.py
spotify_scraper/py.typed
spotify_scraper/auth/__init__.py
spotify_scraper/auth/session.py
spotify_scraper/browsers/__init__.py
spotify_scraper/browsers/base.py
spotify_scraper/browsers/requests_browser.py
spotify_scraper/browsers/selenium_browser.py
spotify_scraper/cli/__init__.py
spotify_scraper/cli/utils.py
spotify_scraper/cli/commands/__init__.py
spotify_scraper/cli/commands/album.py
spotify_scraper/cli/commands/artist.py
spotify_scraper/cli/commands/download.py
spotify_scraper/cli/commands/episode.py
spotify_scraper/cli/commands/playlist.py
spotify_scraper/cli/commands/show.py
spotify_scraper/cli/commands/track.py
spotify_scraper/core/client.py
spotify_scraper/core/config.py
spotify_scraper/core/constants.py
spotify_scraper/core/exceptions.py
spotify_scraper/core/scraper.py
spotify_scraper/core/types.py
spotify_scraper/extractors/__init__.py
spotify_scraper/extractors/album.py
spotify_scraper/extractors/artist.py
spotify_scraper/extractors/episode.py
spotify_scraper/extractors/lyrics.py
spotify_scraper/extractors/playlist.py
spotify_scraper/extractors/show.py
spotify_scraper/extractors/track.py
spotify_scraper/media/__init__.py
spotify_scraper/media/audio.py
spotify_scraper/media/image.py
spotify_scraper/parsers/json_parser.py
spotify_scraper/utils/common.py
spotify_scraper/utils/logger.py
spotify_scraper/utils/url.py
spotifyscraper-2.1.5.dist-info/LICENSE
spotifyscraper-2.1.5.dist-info/METADATA
spotifyscraper-2.1.5.dist-info/WHEEL
spotifyscraper-2.1.5.dist-info/entry_points.txt
spotifyscraper-2.1.5.dist-info/top_level.txt
spotifyscraper-2.1.5.dist-info/RECORD
