Metadata-Version: 2.1
Name: spotifyscraper
Version: 2.1.5
Summary: Python library for extracting data from Spotify without authentication
Author-email: Ali Akhtari <aliakhtari78@hotmail.com>
License: MIT
Project-URL: Homepage, https://github.com/AliAkhtari78/SpotifyScraper
Project-URL: Documentation, https://spotifyscraper.readthedocs.io/
Project-URL: Repository, https://github.com/AliAkhtari78/SpotifyScraper.git
Project-URL: Bug Tracker, https://github.com/AliAkhtari78/SpotifyScraper/issues
Project-URL: Changelog, https://github.com/AliAkhtari78/SpotifyScraper/blob/master/CHANGELOG.md
Keywords: spotify,scraper,music,api,download,podcast,episode,show
Classifier: Development Status :: 5 - Production/Stable
Classifier: Intended Audience :: Developers
Classifier: Operating System :: OS Independent
Classifier: Programming Language :: Python :: 3
Classifier: Programming Language :: Python :: 3.8
Classifier: Programming Language :: Python :: 3.9
Classifier: Programming Language :: Python :: 3.10
Classifier: Programming Language :: Python :: 3.11
Classifier: Programming Language :: Python :: 3.12
Classifier: Topic :: Software Development :: Libraries :: Python Modules
Classifier: Topic :: Multimedia :: Sound/Audio
Requires-Python: >=3.8
Provides-Extra: selenium
Provides-Extra: async
Provides-Extra: dev
Provides-Extra: test
Provides-Extra: docs
Provides-Extra: all
License-File: LICENSE
